ausi/__init__.py
ausi/d3.py
ausi/portfolio.py
ausi/pygal.py
ausi/scipy.py
ausi/d3_templates/bundle/template.html
ausi/d3_templates/d3-force/template.html
ausi/d3_templates/semantic_substrate/template.html
ausi/d3_templates/zoomable_circle_package/COPYRIGHT.md
ausi/d3_templates/zoomable_circle_package/template.html
ausi-0.0.3.dist-info/LICENSE
ausi-0.0.3.dist-info/METADATA
ausi-0.0.3.dist-info/WHEEL
ausi-0.0.3.dist-info/top_level.txt
ausi-0.0.3.dist-info/RECORD
